setup.py
uctypes.py
pycopy_cpython_uctypes.egg-info/PKG-INFO
pycopy_cpython_uctypes.egg-info/SOURCES.txt
pycopy_cpython_uctypes.egg-info/dependency_links.txt
pycopy_cpython_uctypes.egg-info/top_level.txt