Metadata-Version: 1.2
Name: pycopy-cpython-uctypes
Version: 0.1
Summary: Pycopy module uctypes ported to CPython
Home-page: https://github.com/pfalcon/pycopy-lib
Author: Paul Sokolovsky
Author-email: pycopy-dev@googlegroups.com
Maintainer: Paul Sokolovsky
Maintainer-email: pycopy-dev@googlegroups.com
License: Python
Platform: UNKNOWN
